{
	"id": "gY9BjxSoX70gBIE",
	"json": "{\"id\":\"gY9BjxSoX70gBIE\",\"url\":\"http://localhost:3000/real-estate-photographers/in/us/michigan\",\"loadedUrl\":\"http://localhost:3000/real-estate-photographers/in/us/michigan\",\"uniqueKey\":\"http://localhost:3000/real-estate-photographers/in/us/michigan\",\"method\":\"GET\",\"noRetry\":false,\"retryCount\":0,\"errorMessages\":[],\"headers\":{},\"userData\":{\"depth\":1,\"__crawlee\":{\"crawlDepth\":1,\"enqueueStrategy\":\"same-domain\",\"state\":4}},\"handledAt\":\"2025-10-02T13:36:56.591Z\"}",
	"method": "GET",
	"orderNo": null,
	"retryCount": 0,
	"uniqueKey": "http://localhost:3000/real-estate-photographers/in/us/michigan",
	"url": "http://localhost:3000/real-estate-photographers/in/us/michigan"
}